sprinkler/__init__.py
sprinkler/cli.py
sprinkler/constants.py
sprinkler/db.py
sprinkler/exceptions.py
sprinkler/git.py
sprinkler/py.typed
sprinkler/scheduler.py
sprinkler/task_instance.py
sprinkler/task_manager.py
sprinkler/utils.py
sprinkler/webserver.py
sprinkler/.build/index.html
sprinkler/.build/assets/index-8ee4f58f.js
sprinkler/.build/assets/index-dc24b5d6.css
sprinkler/db_interfaces/__init__.py
sprinkler/db_interfaces/api_keys.py
sprinkler/db_interfaces/config.py
sprinkler/db_interfaces/images.py
sprinkler/db_interfaces/py.typed
sprinkler/db_interfaces/secrets.py
sprinkler/db_interfaces/task_instances.py
sprinkler/db_interfaces/users.py
sprinkler/targets/__init__.py
sprinkler/targets/py.typed
sprinkler/targets/sprinkler_config.py
sprinkler/targets/task.py
s7r-0.1.9.dist-info/METADATA
s7r-0.1.9.dist-info/WHEEL
s7r-0.1.9.dist-info/entry_points.txt
s7r-0.1.9.dist-info/top_level.txt
s7r-0.1.9.dist-info/RECORD
